[{"class": "ball", "occlusion": 0, "id": 6, "bounding box (ltrb)": [2615, 1036, 2718, 1147]}, {"class": "ball", "occlusion": 0, "id": 8, "bounding box (ltrb)": [2433, 660, 2552, 779]}, {"class": "ball", "occlusion": 0, "id": 7, "bounding box (ltrb)": [1144, 909, 1254, 1019]}, {"class": "ball", "occlusion": 1, "id": 9, "bounding box (ltrb)": [1735, 1307, 1855, 1424]}, {"class": "person", "id": 1, "bounding box (ltrb)": [991, 760, 1265, 1363]}, {"class": "person", "id": 2, "bounding box (ltrb)": [1558, 411, 1849, 943]}, {"class": "person", "id": 3, "bounding box (ltrb)": [2425, 471, 2653, 1034]}, {"class": "person", "id": 4, "bounding box (ltrb)": [2601, 887, 2963, 1561]}, {"class": "person", "id": 5, "bounding box (ltrb)": [1581, 1185, 1875, 1917]}]