[{"class": "ball", "occlusion": 1, "id": 6, "bounding box (ltrb)": [1718, 1296, 1821, 1407]}, {"class": "ball", "occlusion": 0, "id": 8, "bounding box (ltrb)": [1156, 917, 1275, 1036]}, {"class": "ball", "occlusion": 0, "id": 7, "bounding box (ltrb)": [2626, 936, 2736, 1046]}, {"class": "ball", "occlusion": 0, "id": 9, "bounding box (ltrb)": [2424, 671, 2544, 788]}, {"class": "person", "id": 1, "bounding box (ltrb)": [1011, 753, 1275, 1376]}, {"class": "person", "id": 2, "bounding box (ltrb)": [1561, 418, 1849, 947]}, {"class": "person", "id": 3, "bounding box (ltrb)": [2413, 478, 2647, 1043]}, {"class": "person", "id": 4, "bounding box (ltrb)": [2611, 887, 2946, 1561]}, {"class": "person", "id": 5, "bounding box (ltrb)": [1567, 1189, 1861, 1925]}]