[{"class": "person", "id": 1, "bounding box (ltwh)": [1119, 353, 71, 169]}, {"class": "person", "id": 2, "bounding box (ltwh)": [1032, 365, 72, 190]}, {"class": "person", "id": 3, "bounding box (ltwh)": [1022, 326, 93, 169]}, {"class": "person", "id": 4, "bounding box (ltwh)": [1091, 246, 62, 149]}, {"class": "person", "id": 6, "bounding box (ltwh)": [896, 525, 99, 188]}, {"class": "person", "id": 5, "bounding box (ltwh)": [1447, 372, 74, 179]}, {"class": "ball", "id": 14, "bounding box (ltwh)": [1165, 406, 27, 29]}, {"class": "ball", "id": 12, "bounding box (ltwh)": [956, 626, 38, 37]}, {"class": "ball", "id": 13, "bounding box (ltwh)": [1058, 352, 22, 21]}]