[{"class": "person", "id": 1, "bounding box (ltwh)": [973, 342, 68, 173]}, {"class": "person", "id": 2, "bounding box (ltwh)": [894, 362, 61, 181]}, {"class": "person", "id": 3, "bounding box (ltwh)": [884, 315, 70, 167]}, {"class": "person", "id": 7, "bounding box (ltwh)": [1780, 321, 89, 172]}, {"class": "person", "id": 4, "bounding box (ltwh)": [882, 234, 70, 126]}, {"class": "person", "id": 6, "bounding box (ltwh)": [993, 543, 80, 201]}, {"class": "person", "id": 5, "bounding box (ltwh)": [1289, 358, 82, 177]}, {"class": "ball", "id": 14, "bounding box (ltwh)": [1286, 397, 32, 32]}, {"class": "ball", "id": 12, "bounding box (ltwh)": [1033, 581, 33, 33]}]