[{"class": "person", "id": 1, "bounding box (ltwh)": [941, 346, 69, 168]}, {"class": "person", "id": 2, "bounding box (ltwh)": [850, 355, 61, 182]}, {"class": "person", "id": 3, "bounding box (ltwh)": [862, 311, 78, 165]}, {"class": "person", "id": 7, "bounding box (ltwh)": [1821, 397, 94, 184]}, {"class": "person", "id": 4, "bounding box (ltwh)": [594, 327, 63, 174]}, {"class": "person", "id": 6, "bounding box (ltwh)": [1243, 392, 86, 171]}, {"class": "person", "id": 5, "bounding box (ltwh)": [925, 235, 56, 131]}, {"class": "ball", "id": 14, "bounding box (ltwh)": [919, 260, 23, 23]}, {"class": "ball", "id": 12, "bounding box (ltwh)": [1301, 436, 23, 25]}, {"class": "ball", "id": 13, "bounding box (ltwh)": [630, 352, 29, 31]}]