[{"class": "person", "id": 1, "bounding box (ltwh)": [907, 414, 69, 182]}, {"class": "person", "id": 2, "bounding box (ltwh)": [785, 426, 83, 194]}, {"class": "person", "id": 3, "bounding box (ltwh)": [822, 373, 78, 177]}, {"class": "person", "id": 7, "bounding box (ltwh)": [1867, 482, 52, 209]}, {"class": "person", "id": 4, "bounding box (ltwh)": [513, 475, 72, 208]}, {"class": "person", "id": 6, "bounding box (ltwh)": [1145, 381, 71, 169]}, {"class": "person", "id": 5, "bounding box (ltwh)": [802, 271, 52, 143]}, {"class": "ball", "id": 12, "bounding box (ltwh)": [947, 468, 31, 33]}, {"class": "ball", "id": 13, "bounding box (ltwh)": [786, 473, 32, 33]}]