[{"class": "person", "id": 1, "bounding box (ltwh)": [952, 484, 74, 190]}, {"class": "person", "id": 2, "bounding box (ltwh)": [824, 493, 83, 202]}, {"class": "person", "id": 3, "bounding box (ltwh)": [868, 435, 98, 183]}, {"class": "person", "id": 4, "bounding box (ltwh)": [525, 542, 78, 217]}, {"class": "person", "id": 6, "bounding box (ltwh)": [1203, 437, 79, 191]}, {"class": "person", "id": 5, "bounding box (ltwh)": [780, 326, 67, 153]}, {"class": "ball", "id": 12, "bounding box (ltwh)": [995, 541, 32, 34]}, {"class": "ball", "id": 13, "bounding box (ltwh)": [826, 537, 32, 34]}]