[{"class": "person", "id": 1, "bounding box (ltwh)": [900, 435, 70, 184]}, {"class": "person", "id": 2, "bounding box (ltwh)": [776, 446, 82, 198]}, {"class": "person", "id": 3, "bounding box (ltwh)": [814, 392, 79, 180]}, {"class": "person", "id": 7, "bounding box (ltwh)": [1880, 516, 39, 204]}, {"class": "person", "id": 4, "bounding box (ltwh)": [492, 498, 73, 212]}, {"class": "person", "id": 6, "bounding box (ltwh)": [1141, 389, 67, 179]}, {"class": "person", "id": 5, "bounding box (ltwh)": [788, 289, 54, 146]}, {"class": "ball", "id": 12, "bounding box (ltwh)": [941, 488, 31, 33]}, {"class": "ball", "id": 13, "bounding box (ltwh)": [777, 497, 32, 33]}]