[{"class": "person", "id": 1, "bounding box (ltwh)": [889, 560, 89, 196]}, {"class": "person", "id": 2, "bounding box (ltwh)": [751, 563, 94, 216]}, {"class": "person", "id": 3, "bounding box (ltwh)": [815, 496, 84, 198]}, {"class": "person", "id": 4, "bounding box (ltwh)": [516, 730, 119, 267]}, {"class": "person", "id": 6, "bounding box (ltwh)": [986, 373, 67, 171]}, {"class": "person", "id": 5, "bounding box (ltwh)": [438, 484, 84, 184]}, {"class": "ball", "id": 12, "bounding box (ltwh)": [937, 618, 34, 37]}, {"class": "ball", "id": 13, "bounding box (ltwh)": [751, 627, 35, 36]}]