[{"class": "person", "id": 1, "bounding box (ltwh)": [919, 579, 102, 206]}, {"class": "person", "id": 2, "bounding box (ltwh)": [753, 569, 123, 217]}, {"class": "person", "id": 3, "bounding box (ltwh)": [885, 513, 76, 193]}, {"class": "person", "id": 4, "bounding box (ltwh)": [1117, 679, 130, 238]}, {"class": "person", "id": 6, "bounding box (ltwh)": [941, 375, 70, 167]}, {"class": "person", "id": 5, "bounding box (ltwh)": [381, 596, 121, 222]}, {"class": "ball", "id": 14, "bounding box (ltwh)": [934, 419, 30, 29]}, {"class": "ball", "id": 12, "bounding box (ltwh)": [1075, 656, 45, 43]}, {"class": "ball", "id": 13, "bounding box (ltwh)": [762, 627, 40, 40]}]