[{"class": "person", "id": 1, "bounding box (ltwh)": [933, 583, 99, 203]}, {"class": "person", "id": 2, "bounding box (ltwh)": [776, 565, 114, 221]}, {"class": "person", "id": 3, "bounding box (ltwh)": [900, 514, 77, 194]}, {"class": "person", "id": 4, "bounding box (ltwh)": [1163, 679, 111, 243]}, {"class": "person", "id": 6, "bounding box (ltwh)": [931, 391, 72, 155]}, {"class": "person", "id": 5, "bounding box (ltwh)": [402, 591, 117, 221]}, {"class": "ball", "id": 14, "bounding box (ltwh)": [925, 439, 29, 28]}, {"class": "ball", "id": 12, "bounding box (ltwh)": [1170, 736, 42, 43]}, {"class": "ball", "id": 13, "bounding box (ltwh)": [781, 584, 39, 39]}]