[{"class": "person", "id": 1, "bounding box (ltwh)": [900, 583, 101, 202]}, {"class": "person", "id": 2, "bounding box (ltwh)": [775, 569, 87, 218]}, {"class": "person", "id": 3, "bounding box (ltwh)": [864, 512, 78, 190]}, {"class": "person", "id": 4, "bounding box (ltwh)": [1166, 642, 112, 252]}, {"class": "person", "id": 6, "bounding box (ltwh)": [877, 384, 80, 163]}, {"class": "person", "id": 5, "bounding box (ltwh)": [364, 632, 97, 216]}, {"class": "ball", "id": 14, "bounding box (ltwh)": [872, 434, 28, 28]}, {"class": "ball", "id": 12, "bounding box (ltwh)": [1177, 692, 41, 41]}, {"class": "ball", "id": 13, "bounding box (ltwh)": [387, 712, 43, 40]}]