[{"class": "person", "id": 1, "bounding box (ltwh)": [910, 533, 85, 219]}, {"class": "person", "id": 2, "bounding box (ltwh)": [783, 518, 83, 209]}, {"class": "person", "id": 3, "bounding box (ltwh)": [899, 471, 82, 195]}, {"class": "person", "id": 4, "bounding box (ltwh)": [1112, 370, 99, 179]}, {"class": "person", "id": 6, "bounding box (ltwh)": [487, 496, 88, 193]}, {"class": "person", "id": 5, "bounding box (ltwh)": [1146, 680, 138, 257]}, {"class": "ball", "id": 14, "bounding box (ltwh)": [786, 588, 33, 35]}, {"class": "ball", "id": 12, "bounding box (ltwh)": [945, 527, 29, 29]}, {"class": "ball", "id": 13, "bounding box (ltwh)": [1123, 648, 45, 45]}]