[{"class": "person", "id": 1, "bounding box (ltwh)": [846, 531, 86, 211]}, {"class": "person", "id": 2, "bounding box (ltwh)": [718, 507, 86, 212]}, {"class": "person", "id": 3, "bounding box (ltwh)": [848, 465, 84, 196]}, {"class": "person", "id": 4, "bounding box (ltwh)": [1054, 362, 74, 177]}, {"class": "person", "id": 6, "bounding box (ltwh)": [425, 554, 86, 182]}, {"class": "person", "id": 5, "bounding box (ltwh)": [1136, 660, 125, 232]}, {"class": "ball", "id": 14, "bounding box (ltwh)": [724, 549, 33, 34]}, {"class": "ball", "id": 12, "bounding box (ltwh)": [899, 520, 30, 32]}, {"class": "ball", "id": 13, "bounding box (ltwh)": [890, 577, 40, 42]}]