[{"class": "person", "id": 1, "bounding box (ltwh)": [546, 455, 94, 214]}, {"class": "person", "id": 2, "bounding box (ltwh)": [467, 426, 86, 205]}, {"class": "person", "id": 3, "bounding box (ltwh)": [600, 400, 80, 195]}, {"class": "person", "id": 4, "bounding box (ltwh)": [518, 292, 76, 166]}, {"class": "person", "id": 6, "bounding box (ltwh)": [477, 750, 138, 239]}, {"class": "person", "id": 5, "bounding box (ltwh)": [858, 331, 67, 169]}, {"class": "ball", "id": 14, "bounding box (ltwh)": [469, 464, 25, 26]}, {"class": "ball", "id": 12, "bounding box (ltwh)": [641, 393, 35, 35]}, {"class": "ball", "id": 13, "bounding box (ltwh)": [584, 525, 37, 37]}]