[{"class": "person", "id": 1, "bounding box (ltwh)": [480, 472, 103, 231]}, {"class": "person", "id": 2, "bounding box (ltwh)": [345, 389, 89, 211]}, {"class": "person", "id": 3, "bounding box (ltwh)": [862, 349, 85, 187]}, {"class": "person", "id": 7, "bounding box (ltwh)": [431, 747, 150, 267]}, {"class": "person", "id": 4, "bounding box (ltwh)": [264, 350, 98, 198]}, {"class": "person", "id": 5, "bounding box (ltwh)": [574, 406, 86, 215]}, {"class": "ball", "id": 14, "bounding box (ltwh)": [294, 415, 33, 31]}, {"class": "ball", "id": 12, "bounding box (ltwh)": [589, 477, 37, 36]}, {"class": "ball", "id": 13, "bounding box (ltwh)": [519, 803, 45, 44]}]