[{"class": "person", "id": 1, "bounding box (ltwh)": [511, 694, 145, 300]}, {"class": "person", "id": 2, "bounding box (ltwh)": [417, 253, 106, 200]}, {"class": "person", "id": 3, "bounding box (ltwh)": [1063, 297, 86, 203]}, {"class": "person", "id": 7, "bounding box (ltwh)": [641, 468, 95, 210]}, {"class": "person", "id": 4, "bounding box (ltwh)": [581, 396, 92, 223]}, {"class": "person", "id": 5, "bounding box (ltwh)": [702, 374, 107, 224]}, {"class": "ball", "id": 14, "bounding box (ltwh)": [595, 419, 23, 26]}, {"class": "ball", "id": 12, "bounding box (ltwh)": [822, 343, 37, 37]}, {"class": "ball", "id": 13, "bounding box (ltwh)": [683, 551, 39, 40]}]