[{"class": "person", "id": 1, "bounding box (ltwh)": [546, 706, 177, 333]}, {"class": "person", "id": 2, "bounding box (ltwh)": [348, 274, 105, 181]}, {"class": "person", "id": 3, "bounding box (ltwh)": [920, 283, 94, 192]}, {"class": "person", "id": 7, "bounding box (ltwh)": [597, 454, 99, 223]}, {"class": "person", "id": 4, "bounding box (ltwh)": [551, 388, 76, 222]}, {"class": "person", "id": 5, "bounding box (ltwh)": [667, 389, 72, 212]}, {"class": "ball", "id": 14, "bounding box (ltwh)": [372, 362, 35, 33]}, {"class": "ball", "id": 12, "bounding box (ltwh)": [922, 330, 29, 30]}]