[{"class": "person", "id": 1, "bounding box (ltwh)": [1170, 400, 94, 255]}, {"class": "person", "id": 2, "bounding box (ltwh)": [478, 691, 154, 305]}, {"class": "person", "id": 3, "bounding box (ltwh)": [590, 250, 93, 183]}, {"class": "person", "id": 7, "bounding box (ltwh)": [675, 488, 101, 228]}, {"class": "person", "id": 4, "bounding box (ltwh)": [645, 384, 84, 166]}, {"class": "person", "id": 5, "bounding box (ltwh)": [771, 431, 94, 221]}, {"class": "ball", "id": 14, "bounding box (ltwh)": [535, 735, 50, 50]}, {"class": "ball", "id": 12, "bounding box (ltwh)": [646, 335, 40, 41]}, {"class": "ball", "id": 13, "bounding box (ltwh)": [829, 443, 39, 40]}]