[{"class": "person", "id": 1, "bounding box (ltwh)": [792, 290, 94, 194]}, {"class": "person", "id": 2, "bounding box (ltwh)": [827, 600, 160, 269]}, {"class": "person", "id": 3, "bounding box (ltwh)": [231, 397, 115, 202]}, {"class": "person", "id": 7, "bounding box (ltwh)": [592, 507, 95, 224]}, {"class": "person", "id": 4, "bounding box (ltwh)": [575, 430, 91, 223]}, {"class": "person", "id": 5, "bounding box (ltwh)": [697, 443, 73, 225]}, {"class": "ball", "id": 14, "bounding box (ltwh)": [599, 590, 41, 42]}, {"class": "ball", "id": 13, "bounding box (ltwh)": [728, 513, 40, 41]}]