[{"class": "person", "id": 1, "bounding box (ltwh)": [152, 496, 133, 225]}, {"class": "person", "id": 2, "bounding box (ltwh)": [720, 250, 105, 170]}, {"class": "person", "id": 3, "bounding box (ltwh)": [896, 526, 159, 274]}, {"class": "person", "id": 7, "bounding box (ltwh)": [541, 441, 107, 224]}, {"class": "person", "id": 4, "bounding box (ltwh)": [605, 375, 98, 223]}, {"class": "person", "id": 5, "bounding box (ltwh)": [693, 414, 80, 225]}, {"class": "ball", "id": 12, "bounding box (ltwh)": [538, 464, 46, 44]}, {"class": "ball", "id": 14, "bounding box (ltwh)": [727, 450, 38, 40]}]