[{"class": "person", "id": 1, "bounding box (ltwh)": [973, 499, 156, 269]}, {"class": "person", "id": 2, "bounding box (ltwh)": [451, 338, 91, 236]}, {"class": "person", "id": 3, "bounding box (ltwh)": [1094, 224, 110, 207]}, {"class": "person", "id": 7, "bounding box (ltwh)": [741, 363, 94, 213]}, {"class": "person", "id": 4, "bounding box (ltwh)": [847, 323, 59, 196]}, {"class": "person", "id": 5, "bounding box (ltwh)": [880, 368, 80, 209]}, {"class": "ball", "id": 12, "bounding box (ltwh)": [736, 401, 38, 38]}, {"class": "ball", "id": 14, "bounding box (ltwh)": [959, 395, 39, 41]}, {"class": "ball", "id": 13, "bounding box (ltwh)": [1091, 252, 32, 34]}]