[{"class": "person", "id": 1, "bounding box (ltwh)": [1100, 464, 124, 269]}, {"class": "person", "id": 2, "bounding box (ltwh)": [520, 345, 78, 202]}, {"class": "person", "id": 3, "bounding box (ltwh)": [1088, 228, 130, 183]}, {"class": "person", "id": 7, "bounding box (ltwh)": [835, 353, 63, 204]}, {"class": "person", "id": 4, "bounding box (ltwh)": [924, 312, 72, 201]}, {"class": "person", "id": 5, "bounding box (ltwh)": [940, 364, 73, 206]}, {"class": "ball", "id": 12, "bounding box (ltwh)": [563, 431, 35, 36]}, {"class": "ball", "id": 14, "bounding box (ltwh)": [1108, 527, 29, 32]}, {"class": "ball", "id": 13, "bounding box (ltwh)": [1076, 301, 31, 32]}]