[{"class": "person", "id": 1, "bounding box (ltwh)": [425, 284, 123, 176]}, {"class": "person", "id": 2, "bounding box (ltwh)": [702, 531, 91, 267]}, {"class": "person", "id": 3, "bounding box (ltwh)": [53, 497, 123, 234]}, {"class": "person", "id": 7, "bounding box (ltwh)": [391, 396, 107, 220]}, {"class": "person", "id": 5, "bounding box (ltwh)": [503, 414, 101, 227]}, {"class": "person", "id": 4, "bounding box (ltwh)": [532, 359, 82, 217]}, {"class": "ball", "id": 12, "bounding box (ltwh)": [512, 473, 45, 44]}, {"class": "ball", "id": 14, "bounding box (ltwh)": [577, 393, 37, 35]}, {"class": "ball", "id": 13, "bounding box (ltwh)": [392, 463, 35, 38]}]