[{"class": "person", "id": 1, "bounding box (ltwh)": [634, 294, 96, 204]}, {"class": "person", "id": 2, "bounding box (ltwh)": [1342, 346, 114, 229]}, {"class": "person", "id": 3, "bounding box (ltwh)": [700, 622, 151, 289]}, {"class": "person", "id": 7, "bounding box (ltwh)": [793, 389, 102, 214]}, {"class": "person", "id": 5, "bounding box (ltwh)": [879, 426, 107, 220]}, {"class": "person", "id": 4, "bounding box (ltwh)": [960, 369, 117, 222]}, {"class": "ball", "id": 12, "bounding box (ltwh)": [883, 446, 44, 47]}, {"class": "ball", "id": 14, "bounding box (ltwh)": [1112, 350, 37, 37]}, {"class": "ball", "id": 13, "bounding box (ltwh)": [680, 336, 35, 36]}]