[{"class": "person", "id": 2, "bounding box (ltwh)": [790, 413, 84, 222]}, {"class": "person", "id": 3, "bounding box (ltwh)": [846, 464, 103, 246]}, {"class": "person", "id": 7, "bounding box (ltwh)": [650, 446, 111, 240]}, {"class": "person", "id": 5, "bounding box (ltwh)": [986, 807, 123, 271]}, {"class": "person", "id": 6, "bounding box (ltwh)": [226, 444, 135, 241]}, {"class": "person", "id": 4, "bounding box (ltwh)": [1116, 298, 88, 209]}, {"class": "ball", "id": 12, "bounding box (ltwh)": [890, 521, 45, 46]}, {"class": "ball", "id": 13, "bounding box (ltwh)": [651, 498, 40, 42]}]