[{"class": "person", "id": 2, "bounding box (ltwh)": [845, 385, 68, 224]}, {"class": "person", "id": 3, "bounding box (ltwh)": [877, 434, 122, 240]}, {"class": "person", "id": 7, "bounding box (ltwh)": [736, 426, 82, 229]}, {"class": "person", "id": 5, "bounding box (ltwh)": [1264, 631, 136, 301]}, {"class": "person", "id": 6, "bounding box (ltwh)": [357, 495, 134, 232]}, {"class": "person", "id": 4, "bounding box (ltwh)": [1079, 257, 96, 206]}, {"class": "ball", "id": 12, "bounding box (ltwh)": [1347, 696, 46, 48]}, {"class": "ball", "id": 14, "bounding box (ltwh)": [1087, 290, 33, 35]}, {"class": "ball", "id": 13, "bounding box (ltwh)": [413, 557, 47, 45]}]