[{"class": "person", "id": 2, "bounding box (ltwh)": [849, 376, 63, 225]}, {"class": "person", "id": 3, "bounding box (ltwh)": [893, 430, 105, 235]}, {"class": "person", "id": 7, "bounding box (ltwh)": [740, 423, 78, 227]}, {"class": "person", "id": 5, "bounding box (ltwh)": [1334, 476, 113, 276]}, {"class": "person", "id": 6, "bounding box (ltwh)": [482, 533, 156, 238]}, {"class": "person", "id": 4, "bounding box (ltwh)": [977, 251, 120, 180]}, {"class": "ball", "id": 12, "bounding box (ltwh)": [1406, 525, 30, 32]}, {"class": "ball", "id": 14, "bounding box (ltwh)": [994, 312, 31, 32]}, {"class": "ball", "id": 13, "bounding box (ltwh)": [572, 695, 49, 48]}]