[{"class": "person", "id": 2, "bounding box (ltwh)": [866, 355, 71, 217]}, {"class": "person", "id": 3, "bounding box (ltwh)": [970, 386, 94, 230]}, {"class": "person", "id": 7, "bounding box (ltwh)": [794, 415, 84, 222]}, {"class": "person", "id": 5, "bounding box (ltwh)": [408, 538, 126, 231]}, {"class": "person", "id": 6, "bounding box (ltwh)": [634, 253, 74, 178]}, {"class": "person", "id": 4, "bounding box (ltwh)": [1194, 522, 170, 271]}, {"class": "ball", "id": 12, "bounding box (ltwh)": [636, 316, 35, 33]}, {"class": "ball", "id": 14, "bounding box (ltwh)": [462, 615, 45, 44]}, {"class": "ball", "id": 13, "bounding box (ltwh)": [1113, 399, 40, 41]}]