[{"class": "person", "id": 2, "bounding box (ltwh)": [855, 350, 80, 222]}, {"class": "person", "id": 3, "bounding box (ltwh)": [958, 376, 93, 234]}, {"class": "person", "id": 7, "bounding box (ltwh)": [801, 420, 85, 219]}, {"class": "person", "id": 5, "bounding box (ltwh)": [1060, 577, 176, 272]}, {"class": "person", "id": 6, "bounding box (ltwh)": [424, 376, 106, 184]}, {"class": "person", "id": 4, "bounding box (ltwh)": [1250, 326, 91, 221]}, {"class": "ball", "id": 12, "bounding box (ltwh)": [805, 444, 37, 38]}, {"class": "ball", "id": 14, "bounding box (ltwh)": [1167, 646, 49, 48]}, {"class": "ball", "id": 13, "bounding box (ltwh)": [1250, 391, 38, 39]}]