[{"class": "person", "id": 2, "bounding box (ltwh)": [853, 350, 78, 226]}, {"class": "person", "id": 3, "bounding box (ltwh)": [955, 376, 101, 236]}, {"class": "person", "id": 7, "bounding box (ltwh)": [788, 421, 92, 220]}, {"class": "person", "id": 5, "bounding box (ltwh)": [924, 596, 172, 278]}, {"class": "person", "id": 6, "bounding box (ltwh)": [441, 348, 107, 196]}, {"class": "person", "id": 4, "bounding box (ltwh)": [1294, 355, 103, 254]}, {"class": "ball", "id": 12, "bounding box (ltwh)": [706, 348, 39, 40]}, {"class": "ball", "id": 14, "bounding box (ltwh)": [1044, 665, 46, 48]}]