[{"class": "person", "id": 2, "bounding box (ltwh)": [854, 349, 83, 220]}, {"class": "person", "id": 3, "bounding box (ltwh)": [973, 370, 105, 233]}, {"class": "person", "id": 7, "bounding box (ltwh)": [809, 421, 91, 216]}, {"class": "person", "id": 5, "bounding box (ltwh)": [1299, 469, 132, 258]}, {"class": "person", "id": 6, "bounding box (ltwh)": [419, 582, 127, 269]}, {"class": "person", "id": 4, "bounding box (ltwh)": [985, 237, 87, 177]}, {"class": "ball", "id": 12, "bounding box (ltwh)": [813, 499, 40, 40]}, {"class": "ball", "id": 14, "bounding box (ltwh)": [1167, 408, 38, 38]}, {"class": "ball", "id": 13, "bounding box (ltwh)": [1010, 269, 33, 33]}]