[{"class": "person", "id": 2, "bounding box (ltwh)": [853, 347, 83, 224]}, {"class": "person", "id": 3, "bounding box (ltwh)": [973, 371, 105, 233]}, {"class": "person", "id": 7, "bounding box (ltwh)": [807, 422, 93, 216]}, {"class": "person", "id": 5, "bounding box (ltwh)": [1319, 469, 116, 255]}, {"class": "person", "id": 6, "bounding box (ltwh)": [444, 595, 126, 277]}, {"class": "person", "id": 4, "bounding box (ltwh)": [943, 232, 114, 176]}, {"class": "ball", "id": 12, "bounding box (ltwh)": [816, 499, 41, 42]}, {"class": "ball", "id": 14, "bounding box (ltwh)": [1097, 404, 38, 39]}, {"class": "ball", "id": 13, "bounding box (ltwh)": [975, 254, 33, 34]}]