[{"class": "person", "id": 2, "bounding box (ltwh)": [844, 345, 81, 222]}, {"class": "person", "id": 3, "bounding box (ltwh)": [969, 369, 93, 230]}, {"class": "person", "id": 7, "bounding box (ltwh)": [814, 423, 90, 213]}, {"class": "person", "id": 5, "bounding box (ltwh)": [1342, 418, 95, 252]}, {"class": "person", "id": 6, "bounding box (ltwh)": [539, 669, 125, 292]}, {"class": "person", "id": 4, "bounding box (ltwh)": [848, 234, 70, 163]}, {"class": "ball", "id": 12, "bounding box (ltwh)": [827, 500, 40, 41]}, {"class": "ball", "id": 14, "bounding box (ltwh)": [1024, 451, 35, 36]}]