[{"class": "person", "id": 2, "bounding box (ltwh)": [879, 346, 81, 223]}, {"class": "person", "id": 3, "bounding box (ltwh)": [1006, 351, 99, 214]}, {"class": "person", "id": 7, "bounding box (ltwh)": [898, 419, 86, 215]}, {"class": "person", "id": 5, "bounding box (ltwh)": [723, 576, 123, 272]}, {"class": "person", "id": 6, "bounding box (ltwh)": [955, 221, 102, 166]}, {"class": "person", "id": 4, "bounding box (ltwh)": [1317, 364, 93, 226]}, {"class": "ball", "id": 12, "bounding box (ltwh)": [1325, 404, 39, 41]}, {"class": "ball", "id": 14, "bounding box (ltwh)": [947, 324, 29, 30]}, {"class": "ball", "id": 13, "bounding box (ltwh)": [791, 623, 31, 35]}]