[{"class": "person", "id": 2, "bounding box (ltwh)": [841, 337, 79, 216]}, {"class": "person", "id": 3, "bounding box (ltwh)": [944, 324, 82, 205]}, {"class": "person", "id": 7, "bounding box (ltwh)": [893, 404, 95, 204]}, {"class": "person", "id": 5, "bounding box (ltwh)": [1240, 279, 70, 195]}, {"class": "person", "id": 6, "bounding box (ltwh)": [753, 602, 109, 267]}, {"class": "person", "id": 4, "bounding box (ltwh)": [651, 245, 95, 189]}, {"class": "ball", "id": 12, "bounding box (ltwh)": [1238, 300, 34, 35]}, {"class": "ball", "id": 14, "bounding box (ltwh)": [715, 264, 33, 34]}, {"class": "ball", "id": 13, "bounding box (ltwh)": [919, 476, 38, 37]}]