[{"class": "person", "id": 2, "bounding box (ltwh)": [849, 322, 77, 213]}, {"class": "person", "id": 3, "bounding box (ltwh)": [953, 300, 77, 200]}, {"class": "person", "id": 7, "bounding box (ltwh)": [952, 374, 86, 206]}, {"class": "person", "id": 5, "bounding box (ltwh)": [784, 218, 74, 169]}, {"class": "person", "id": 6, "bounding box (ltwh)": [1181, 580, 111, 289]}, {"class": "person", "id": 4, "bounding box (ltwh)": [645, 456, 115, 235]}, {"class": "ball", "id": 12, "bounding box (ltwh)": [786, 248, 24, 28]}, {"class": "ball", "id": 14, "bounding box (ltwh)": [718, 530, 40, 39]}, {"class": "ball", "id": 13, "bounding box (ltwh)": [1156, 484, 43, 44]}]