[{"class": "person", "id": 1, "bounding box (ltwh)": [1487, 784, 218, 295]}, {"class": "person", "id": 2, "bounding box (ltwh)": [874, 309, 70, 219]}, {"class": "person", "id": 3, "bounding box (ltwh)": [957, 287, 79, 202]}, {"class": "person", "id": 7, "bounding box (ltwh)": [977, 368, 82, 208]}, {"class": "person", "id": 5, "bounding box (ltwh)": [592, 236, 74, 180]}, {"class": "person", "id": 6, "bounding box (ltwh)": [1465, 714, 174, 250]}, {"class": "person", "id": 4, "bounding box (ltwh)": [725, 463, 102, 243]}, {"class": "ball", "id": 12, "bounding box (ltwh)": [594, 289, 32, 32]}, {"class": "ball", "id": 13, "bounding box (ltwh)": [1018, 446, 37, 39]}]