[{"class": "person", "id": 1, "bounding box (ltwh)": [1231, 228, 86, 201]}, {"class": "person", "id": 2, "bounding box (ltwh)": [874, 298, 77, 208]}, {"class": "person", "id": 3, "bounding box (ltwh)": [931, 265, 81, 193]}, {"class": "person", "id": 7, "bounding box (ltwh)": [1009, 327, 73, 197]}, {"class": "person", "id": 5, "bounding box (ltwh)": [611, 411, 87, 217]}, {"class": "person", "id": 4, "bounding box (ltwh)": [1263, 388, 103, 218]}, {"class": "ball", "id": 12, "bounding box (ltwh)": [874, 347, 33, 34]}]