[{"class": "person", "id": 1, "bounding box (ltwh)": [1669, 295, 97, 191]}, {"class": "person", "id": 2, "bounding box (ltwh)": [1369, 340, 106, 201]}, {"class": "person", "id": 3, "bounding box (ltwh)": [1286, 306, 87, 197]}, {"class": "person", "id": 7, "bounding box (ltwh)": [1440, 318, 83, 180]}, {"class": "person", "id": 5, "bounding box (ltwh)": [1346, 226, 57, 127]}, {"class": "person", "id": 4, "bounding box (ltwh)": [1274, 469, 106, 235]}, {"class": "ball", "id": 12, "bounding box (ltwh)": [1498, 362, 23, 27]}, {"class": "ball", "id": 14, "bounding box (ltwh)": [1308, 373, 32, 31]}, {"class": "ball", "id": 13, "bounding box (ltwh)": [1401, 415, 33, 32]}]