[{"class": "person", "id": 1, "bounding box (ltwh)": [1748, 418, 111, 221]}, {"class": "person", "id": 2, "bounding box (ltwh)": [1436, 354, 109, 203]}, {"class": "person", "id": 3, "bounding box (ltwh)": [1352, 323, 83, 198]}, {"class": "person", "id": 7, "bounding box (ltwh)": [1508, 315, 85, 196]}, {"class": "person", "id": 5, "bounding box (ltwh)": [1596, 243, 70, 169]}, {"class": "person", "id": 4, "bounding box (ltwh)": [1114, 351, 92, 190]}, {"class": "ball", "id": 12, "bounding box (ltwh)": [1565, 296, 33, 33]}, {"class": "ball", "id": 14, "bounding box (ltwh)": [1352, 358, 32, 32]}, {"class": "ball", "id": 13, "bounding box (ltwh)": [1474, 417, 35, 34]}]