[{"class": "person", "id": 1, "bounding box (ltwh)": [1414, 514, 128, 244]}, {"class": "person", "id": 2, "bounding box (ltwh)": [1240, 399, 106, 208]}, {"class": "person", "id": 3, "bounding box (ltwh)": [1127, 370, 91, 206]}, {"class": "person", "id": 7, "bounding box (ltwh)": [1277, 357, 73, 181]}, {"class": "person", "id": 5, "bounding box (ltwh)": [1350, 264, 87, 161]}, {"class": "person", "id": 6, "bounding box (ltwh)": [1616, 136, 67, 139]}, {"class": "person", "id": 4, "bounding box (ltwh)": [852, 349, 92, 193]}, {"class": "ball", "id": 12, "bounding box (ltwh)": [1373, 312, 30, 30]}, {"class": "ball", "id": 14, "bounding box (ltwh)": [1076, 332, 34, 33]}, {"class": "ball", "id": 13, "bounding box (ltwh)": [1295, 481, 35, 35]}]