[{"class": "person", "id": 1, "bounding box (ltwh)": [214, 689, 174, 287]}, {"class": "person", "id": 2, "bounding box (ltwh)": [708, 545, 85, 242]}, {"class": "person", "id": 3, "bounding box (ltwh)": [571, 546, 89, 254]}, {"class": "person", "id": 7, "bounding box (ltwh)": [679, 495, 81, 200]}, {"class": "person", "id": 5, "bounding box (ltwh)": [1054, 524, 82, 211]}, {"class": "person", "id": 6, "bounding box (ltwh)": [829, 162, 55, 138]}, {"class": "person", "id": 4, "bounding box (ltwh)": [516, 385, 97, 190]}, {"class": "ball", "id": 12, "bounding box (ltwh)": [1053, 579, 39, 38]}, {"class": "ball", "id": 14, "bounding box (ltwh)": [574, 454, 32, 32]}, {"class": "ball", "id": 13, "bounding box (ltwh)": [217, 765, 47, 49]}]