[{"class": "person", "id": 1, "bounding box (ltwh)": [235, 653, 156, 278]}, {"class": "person", "id": 2, "bounding box (ltwh)": [788, 567, 92, 242]}, {"class": "person", "id": 3, "bounding box (ltwh)": [623, 571, 111, 245]}, {"class": "person", "id": 7, "bounding box (ltwh)": [753, 516, 81, 197]}, {"class": "person", "id": 5, "bounding box (ltwh)": [1171, 676, 81, 255]}, {"class": "person", "id": 6, "bounding box (ltwh)": [879, 171, 54, 139]}, {"class": "person", "id": 4, "bounding box (ltwh)": [715, 371, 86, 175]}, {"class": "ball", "id": 12, "bounding box (ltwh)": [1144, 744, 47, 46]}, {"class": "ball", "id": 14, "bounding box (ltwh)": [733, 397, 35, 33]}, {"class": "ball", "id": 13, "bounding box (ltwh)": [447, 640, 47, 46]}]