[{"class": "ball", "occlusion": 0, "id": 7, "bounding box (ltrb)": [1887, 648, 1964, 731]}, {"class": "ball", "occlusion": 0, "id": 6, "bounding box (ltrb)": [1734, 1090, 1808, 1166]}, {"class": "person", "id": 5, "bounding box (ltrb)": [1841, 513, 2012, 892]}, {"class": "person", "id": 4, "bounding box (ltrb)": [2088, 706, 2290, 1060]}, {"class": "person", "id": 2, "bounding box (ltrb)": [2007, 1273, 2229, 1743]}, {"class": "person", "id": 1, "bounding box (ltrb)": [2465, 1055, 2741, 1478]}, {"class": "person", "id": 3, "bounding box (ltrb)": [1560, 1047, 1844, 1453]}]