[{"class": "person", "id": 2, "bounding box (ltrb)": [1764, 826, 2021, 1249]}, {"class": "person", "id": 4, "bounding box (ltrb)": [1338, 582, 1553, 955]}, {"class": "person", "id": 5, "bounding box (ltrb)": [1938, 469, 2161, 869]}, {"class": "person", "id": 1, "bounding box (ltrb)": [2164, 914, 2431, 1354]}, {"class": "person", "id": 3, "bounding box (ltrb)": [2210, 1143, 2473, 1612]}, {"class": "ball", "occlusion": 0, "id": 7, "bounding box (ltrb)": [1744, 924, 1824, 1007]}, {"class": "ball", "occlusion": 0, "id": 6, "bounding box (ltrb)": [1399, 762, 1488, 857]}]