[{"class": "person", "id": 2, "bounding box (ltrb)": [1456, 894, 1743, 1309]}, {"class": "person", "id": 4, "bounding box (ltrb)": [1008, 1073, 1287, 1483]}, {"class": "person", "id": 5, "bounding box (ltrb)": [1547, 1480, 1857, 2061]}, {"class": "person", "id": 1, "bounding box (ltrb)": [2216, 1395, 2517, 1867]}, {"class": "person", "id": 3, "bounding box (ltrb)": [2135, 817, 2338, 1286]}, {"class": "ball", "occlusion": 1, "id": 7, "bounding box (ltrb)": [1164, 1232, 1255, 1321]}, {"class": "ball", "occlusion": 1, "id": 6, "bounding box (ltrb)": [1735, 1507, 1824, 1602]}]