[{"class": "person", "id": 2, "bounding box (ltrb)": [1476, 1104, 1773, 1551]}, {"class": "person", "id": 4, "bounding box (ltrb)": [982, 1093, 1235, 1530]}, {"class": "person", "id": 5, "bounding box (ltrb)": [1751, 1134, 2023, 1691]}, {"class": "person", "id": 1, "bounding box (ltrb)": [2281, 1327, 2582, 1750]}, {"class": "person", "id": 3, "bounding box (ltrb)": [2176, 713, 2460, 1117]}, {"class": "ball", "occlusion": 1, "id": 7, "bounding box (ltrb)": [1114, 1206, 1205, 1295]}, {"class": "ball", "occlusion": 1, "id": 6, "bounding box (ltrb)": [1873, 1241, 1962, 1336]}]