[{"class": "person", "id": 2, "bounding box (ltrb)": [1724, 585, 1990, 1021]}, {"class": "person", "id": 4, "bounding box (ltrb)": [2193, 246, 2379, 652]}, {"class": "person", "id": 5, "bounding box (ltrb)": [2588, 489, 2835, 919]}, {"class": "person", "id": 1, "bounding box (ltrb)": [1763, 255, 2016, 699]}, {"class": "person", "id": 3, "bounding box (ltrb)": [2021, 798, 2271, 1264]}, {"class": "ball", "occlusion": 0, "id": 7, "bounding box (ltrb)": [2148, 942, 2239, 1031]}, {"class": "ball", "occlusion": 1, "id": 6, "bounding box (ltrb)": [2241, 337, 2330, 432]}]