[{"class": "ball", "occlusion": 0, "id": 7, "bounding box (ltrb)": [1745, 488, 1822, 571]}, {"class": "ball", "occlusion": 0, "id": 6, "bounding box (ltrb)": [1513, 739, 1592, 822]}, {"class": "person", "id": 5, "bounding box (ltrb)": [2458, 800, 2637, 1220]}, {"class": "person", "id": 4, "bounding box (ltrb)": [2215, 428, 2414, 811]}, {"class": "person", "id": 2, "bounding box (ltrb)": [1435, 586, 1629, 998]}, {"class": "person", "id": 1, "bounding box (ltrb)": [1629, 900, 1865, 1369]}, {"class": "person", "id": 3, "bounding box (ltrb)": [1716, 315, 1907, 745]}]