[{"class": "ball", "occlusion": 0, "id": 7, "bounding box (ltrb)": [1510, 597, 1587, 680]}, {"class": "ball", "occlusion": 2, "id": 6, "bounding box (ltrb)": [1011, 1310, 1090, 1393]}, {"class": "person", "id": 5, "bounding box (ltrb)": [1997, 538, 2161, 972]}, {"class": "person", "id": 4, "bounding box (ltrb)": [932, 1209, 1188, 1681]}, {"class": "person", "id": 2, "bounding box (ltrb)": [1477, 451, 1640, 852]}, {"class": "person", "id": 1, "bounding box (ltrb)": [933, 702, 1160, 1106]}, {"class": "person", "id": 3, "bounding box (ltrb)": [1749, 1034, 2002, 1535]}]