[{"class": "ball", "occlusion": 0, "id": 7, "bounding box (ltrb)": [2079, 874, 2156, 957]}, {"class": "ball", "occlusion": 0, "id": 6, "bounding box (ltrb)": [2052, 676, 2131, 759]}, {"class": "person", "id": 5, "bounding box (ltrb)": [1429, 583, 1617, 958]}, {"class": "person", "id": 4, "bounding box (ltrb)": [2016, 518, 2180, 890]}, {"class": "person", "id": 2, "bounding box (ltrb)": [2046, 891, 2298, 1358]}, {"class": "person", "id": 1, "bounding box (ltrb)": [1602, 1261, 1904, 1720]}, {"class": "person", "id": 3, "bounding box (ltrb)": [1207, 1005, 1421, 1439]}]