[{"class": "person", "id": 2, "bounding box (ltrb)": [1358, 626, 1594, 1053]}, {"class": "person", "id": 4, "bounding box (ltrb)": [1148, 1242, 1392, 1682]}, {"class": "person", "id": 5, "bounding box (ltrb)": [2358, 636, 2571, 1027]}, {"class": "person", "id": 1, "bounding box (ltrb)": [2106, 951, 2375, 1440]}, {"class": "person", "id": 3, "bounding box (ltrb)": [1810, 632, 2047, 1032]}, {"class": "ball", "occlusion": 2, "id": 7, "bounding box (ltrb)": [2211, 1080, 2296, 1164]}, {"class": "ball", "occlusion": 1, "id": 6, "bounding box (ltrb)": [2365, 751, 2454, 846]}]