[{"class": "person", "id": 3, "bounding box (ltrb)": [1187, 617, 1403, 1078]}, {"class": "person", "id": 4, "bounding box (ltrb)": [1995, 530, 2171, 930]}, {"class": "person", "id": 5, "bounding box (ltrb)": [2517, 958, 2703, 1426]}, {"class": "person", "id": 1, "bounding box (ltrb)": [1520, 1643, 1830, 2159]}, {"class": "person", "id": 2, "bounding box (ltrb)": [733, 1161, 1031, 1692]}, {"class": "ball", "occlusion": 0, "id": 7, "bounding box (ltrb)": [1256, 757, 1323, 830]}, {"class": "ball", "occlusion": 0, "id": 9, "bounding box (ltrb)": [2031, 660, 2104, 731]}, {"class": "ball", "occlusion": 0, "id": 6, "bounding box (ltrb)": [838, 1187, 938, 1289]}, {"class": "ball", "occlusion": 0, "id": 10, "bounding box (ltrb)": [2510, 1060, 2591, 1143]}, {"class": "ball", "occlusion": 0, "id": 8, "bounding box (ltrb)": [1546, 1736, 1653, 1841]}]