[{"class": "person", "id": 3, "bounding box (ltrb)": [1622, 479, 1799, 890]}, {"class": "person", "id": 4, "bounding box (ltrb)": [2381, 544, 2587, 944]}, {"class": "person", "id": 5, "bounding box (ltrb)": [2550, 1025, 2754, 1515]}, {"class": "person", "id": 1, "bounding box (ltrb)": [1207, 1367, 1503, 1934]}, {"class": "person", "id": 2, "bounding box (ltrb)": [910, 741, 1220, 1235]}, {"class": "ball", "occlusion": 0, "id": 7, "bounding box (ltrb)": [1641, 607, 1708, 680]}, {"class": "ball", "occlusion": 0, "id": 9, "bounding box (ltrb)": [2426, 673, 2499, 744]}, {"class": "ball", "occlusion": 0, "id": 6, "bounding box (ltrb)": [1364, 1450, 1464, 1552]}, {"class": "ball", "occlusion": 0, "id": 10, "bounding box (ltrb)": [2565, 1133, 2652, 1217]}, {"class": "ball", "occlusion": 0, "id": 8, "bounding box (ltrb)": [973, 950, 1061, 1026]}]