[{"class": "person", "id": 3, "bounding box (ltrb)": [1787, 458, 1964, 869]}, {"class": "person", "id": 4, "bounding box (ltrb)": [2575, 586, 2756, 999]}, {"class": "person", "id": 5, "bounding box (ltrb)": [2450, 1120, 2706, 1610]}, {"class": "person", "id": 1, "bounding box (ltrb)": [1069, 1247, 1365, 1814]}, {"class": "person", "id": 2, "bounding box (ltrb)": [1057, 690, 1334, 1177]}, {"class": "ball", "occlusion": 0, "id": 7, "bounding box (ltrb)": [1842, 589, 1909, 658]}, {"class": "ball", "occlusion": 0, "id": 9, "bounding box (ltrb)": [2592, 715, 2665, 786]}, {"class": "ball", "occlusion": 0, "id": 6, "bounding box (ltrb)": [1218, 1333, 1318, 1435]}, {"class": "ball", "occlusion": 0, "id": 10, "bounding box (ltrb)": [2498, 1179, 2585, 1263]}, {"class": "ball", "occlusion": 0, "id": 8, "bounding box (ltrb)": [1156, 793, 1236, 875]}]