[{"class": "person", "id": 3, "bounding box (ltrb)": [2164, 498, 2323, 923]}, {"class": "person", "id": 4, "bounding box (ltrb)": [2448, 898, 2651, 1389]}, {"class": "person", "id": 5, "bounding box (ltrb)": [1425, 1282, 1702, 1832]}, {"class": "person", "id": 1, "bounding box (ltrb)": [622, 765, 918, 1332]}, {"class": "person", "id": 2, "bounding box (ltrb)": [1292, 473, 1511, 929]}, {"class": "ball", "occlusion": 0, "id": 7, "bounding box (ltrb)": [2157, 620, 2221, 687]}, {"class": "ball", "occlusion": 0, "id": 9, "bounding box (ltrb)": [2456, 977, 2539, 1055]}, {"class": "ball", "occlusion": 0, "id": 6, "bounding box (ltrb)": [779, 904, 862, 983]}, {"class": "ball", "occlusion": 0, "id": 10, "bounding box (ltrb)": [1369, 526, 1435, 592]}, {"class": "ball", "occlusion": 0, "id": 8, "bounding box (ltrb)": [1572, 1377, 1661, 1480]}]