[{"class": "person", "id": 3, "bounding box (ltrb)": [2223, 633, 2398, 1079]}, {"class": "person", "id": 4, "bounding box (ltrb)": [1992, 1111, 2224, 1602]}, {"class": "person", "id": 5, "bounding box (ltrb)": [784, 1110, 1061, 1660]}, {"class": "person", "id": 1, "bounding box (ltrb)": [729, 542, 967, 992]}, {"class": "person", "id": 2, "bounding box (ltrb)": [1429, 395, 1660, 804]}, {"class": "ball", "occlusion": 0, "id": 7, "bounding box (ltrb)": [2229, 761, 2293, 828]}, {"class": "ball", "occlusion": 0, "id": 9, "bounding box (ltrb)": [1532, 519, 1592, 587]}, {"class": "ball", "occlusion": 0, "id": 6, "bounding box (ltrb)": [849, 665, 923, 734]}, {"class": "ball", "occlusion": 0, "id": 10, "bounding box (ltrb)": [2001, 1249, 2086, 1334]}, {"class": "ball", "occlusion": 0, "id": 8, "bounding box (ltrb)": [927, 1225, 1020, 1316]}]