[{"class": "ball", "occlusion": 0, "id": 10, "bounding box (ltrb)": [2574, 840, 2648, 913]}, {"class": "ball", "occlusion": 0, "id": 9, "bounding box (ltrb)": [1770, 685, 1850, 761]}, {"class": "ball", "occlusion": 0, "id": 6, "bounding box (ltrb)": [969, 982, 1053, 1058]}, {"class": "ball", "occlusion": 0, "id": 7, "bounding box (ltrb)": [2227, 541, 2292, 604]}, {"class": "ball", "occlusion": 2, "id": 8, "bounding box (ltrb)": [1834, 1244, 1874, 1283]}, {"class": "person", "id": 5, "bounding box (ltrb)": [1356, 432, 1527, 850]}, {"class": "person", "id": 4, "bounding box (ltrb)": [849, 848, 1065, 1325]}, {"class": "person", "id": 3, "bounding box (ltrb)": [1696, 1122, 1908, 1653]}, {"class": "person", "id": 2, "bounding box (ltrb)": [2530, 754, 2783, 1233]}, {"class": "person", "id": 1, "bounding box (ltrb)": [2219, 419, 2380, 808]}]