[{"class": "person", "id": 3, "bounding box (ltrb)": [2261, 1089, 2498, 1615]}, {"class": "person", "id": 4, "bounding box (ltrb)": [1226, 1075, 1510, 1595]}, {"class": "person", "id": 5, "bounding box (ltrb)": [1157, 585, 1326, 1005]}, {"class": "person", "id": 1, "bounding box (ltrb)": [1951, 374, 2123, 751]}, {"class": "person", "id": 2, "bounding box (ltrb)": [2489, 565, 2767, 1017]}, {"class": "ball", "occlusion": 0, "id": 7, "bounding box (ltrb)": [1168, 713, 1231, 778]}, {"class": "ball", "occlusion": 0, "id": 9, "bounding box (ltrb)": [1989, 492, 2053, 559]}, {"class": "ball", "occlusion": 0, "id": 6, "bounding box (ltrb)": [1816, 1496, 1900, 1583]}, {"class": "ball", "occlusion": 0, "id": 10, "bounding box (ltrb)": [2554, 685, 2621, 753]}, {"class": "ball", "occlusion": 0, "id": 8, "bounding box (ltrb)": [1992, 975, 2085, 1069]}]