[{"class": "ball", "occlusion": 0, "id": 10, "bounding box (ltrb)": [1806, 1038, 1902, 1126]}, {"class": "ball", "occlusion": 0, "id": 9, "bounding box (ltrb)": [1965, 505, 2027, 566]}, {"class": "ball", "occlusion": 0, "id": 6, "bounding box (ltrb)": [2761, 1217, 2848, 1303]}, {"class": "ball", "occlusion": 0, "id": 7, "bounding box (ltrb)": [1263, 897, 1347, 970]}, {"class": "ball", "occlusion": 0, "id": 8, "bounding box (ltrb)": [2562, 680, 2627, 747]}, {"class": "person", "id": 5, "bounding box (ltrb)": [1223, 756, 1392, 1191]}, {"class": "person", "id": 4, "bounding box (ltrb)": [1682, 1075, 1949, 1655]}, {"class": "person", "id": 3, "bounding box (ltrb)": [2697, 1092, 2966, 1638]}, {"class": "person", "id": 2, "bounding box (ltrb)": [2511, 550, 2721, 974]}, {"class": "person", "id": 1, "bounding box (ltrb)": [1915, 405, 2084, 786]}]