[{"class": "person", "id": 3, "bounding box (ltrb)": [2727, 842, 3011, 1382]}, {"class": "person", "id": 4, "bounding box (ltrb)": [2169, 1364, 2409, 1951]}, {"class": "person", "id": 5, "bounding box (ltrb)": [1153, 1046, 1363, 1551]}, {"class": "person", "id": 1, "bounding box (ltrb)": [1421, 498, 1593, 899]}, {"class": "person", "id": 2, "bounding box (ltrb)": [2151, 446, 2370, 898]}, {"class": "ball", "occlusion": 1, "id": 7, "bounding box (ltrb)": [2247, 1443, 2332, 1529]}, {"class": "ball", "occlusion": 0, "id": 9, "bounding box (ltrb)": [1263, 1159, 1358, 1254]}, {"class": "ball", "occlusion": 0, "id": 6, "bounding box (ltrb)": [2793, 886, 2880, 974]}, {"class": "ball", "occlusion": 0, "id": 10, "bounding box (ltrb)": [1510, 613, 1573, 675]}, {"class": "ball", "occlusion": 0, "id": 8, "bounding box (ltrb)": [2199, 558, 2268, 627]}]