[{"class": "ball", "occlusion": 0, "id": 10, "bounding box (ltrb)": [1241, 657, 1315, 730]}, {"class": "ball", "occlusion": 0, "id": 9, "bounding box (ltrb)": [1254, 1229, 1346, 1322]}, {"class": "ball", "occlusion": 0, "id": 6, "bounding box (ltrb)": [1913, 573, 1978, 635]}, {"class": "ball", "occlusion": 0, "id": 7, "bounding box (ltrb)": [2414, 1347, 2497, 1433]}, {"class": "ball", "occlusion": 0, "id": 8, "bounding box (ltrb)": [2366, 927, 2437, 1003]}, {"class": "person", "id": 5, "bounding box (ltrb)": [1121, 1130, 1362, 1656]}, {"class": "person", "id": 4, "bounding box (ltrb)": [2322, 1223, 2621, 1786]}, {"class": "person", "id": 3, "bounding box (ltrb)": [2430, 692, 2727, 1169]}, {"class": "person", "id": 2, "bounding box (ltrb)": [1812, 431, 2032, 812]}, {"class": "person", "id": 1, "bounding box (ltrb)": [1138, 535, 1325, 963]}]