[{"class": "person", "id": 7, "bounding box (ltrb)": [1558, 231, 1629, 389]}, {"class": "person", "id": 5, "bounding box (ltrb)": [609, 561, 709, 781]}, {"class": "person", "id": 4, "bounding box (ltrb)": [1121, 433, 1212, 642]}, {"class": "person", "id": 2, "bounding box (ltrb)": [842, 385, 914, 576]}, {"class": "person", "id": 3, "bounding box (ltrb)": [796, 342, 867, 527]}, {"class": "person", "id": 6, "bounding box (ltrb)": [566, 320, 643, 470]}, {"class": "person", "id": 1, "bounding box (ltrb)": [907, 360, 969, 536]}, {"class": "ball", "occlusion": 1, "id": 13, "bounding box (ltrb)": [799, 374, 828, 400]}, {"class": "ball", "occlusion": 0, "id": 12, "bounding box (ltrb)": [708, 476, 747, 514]}]