[{"class": "ball", "occlusion": 2, "id": 13, "bounding box (ltrb)": [1122, 369, 1146, 388]}, {"class": "ball", "occlusion": 0, "id": 12, "bounding box (ltrb)": [847, 459, 882, 495]}, {"class": "ball", "occlusion": 0, "id": 14, "bounding box (ltrb)": [1236, 404, 1267, 436]}, {"class": "person", "id": 5, "bounding box (ltrb)": [1470, 473, 1563, 675]}, {"class": "person", "id": 6, "bounding box (ltrb)": [799, 434, 881, 626]}, {"class": "person", "id": 4, "bounding box (ltrb)": [1325, 282, 1388, 451]}, {"class": "person", "id": 3, "bounding box (ltrb)": [1091, 327, 1162, 508]}, {"class": "person", "id": 2, "bounding box (ltrb)": [1105, 373, 1169, 560]}, {"class": "person", "id": 1, "bounding box (ltrb)": [1194, 355, 1272, 527]}]