[{"class": "person", "id": 7, "bounding box (ltrb)": [1841, 425, 1919, 608]}, {"class": "person", "id": 5, "bounding box (ltrb)": [869, 243, 929, 365]}, {"class": "person", "id": 4, "bounding box (ltrb)": [592, 362, 658, 557]}, {"class": "person", "id": 2, "bounding box (ltrb)": [826, 365, 913, 552]}, {"class": "person", "id": 3, "bounding box (ltrb)": [872, 317, 966, 492]}, {"class": "person", "id": 6, "bounding box (ltrb)": [1213, 381, 1318, 563]}, {"class": "person", "id": 1, "bounding box (ltrb)": [947, 358, 1018, 529]}, {"class": "ball", "occlusion": 0, "id": 13, "bounding box (ltrb)": [768, 362, 799, 395]}, {"class": "ball", "occlusion": 0, "id": 12, "bounding box (ltrb)": [1215, 380, 1247, 411]}, {"class": "ball", "occlusion": 0, "id": 14, "bounding box (ltrb)": [887, 285, 909, 308]}]