[{"class": "person", "id": 5, "bounding box (ltrb)": [480, 468, 575, 638]}, {"class": "person", "id": 4, "bounding box (ltrb)": [517, 707, 617, 936]}, {"class": "person", "id": 2, "bounding box (ltrb)": [764, 556, 859, 773]}, {"class": "person", "id": 3, "bounding box (ltrb)": [824, 495, 910, 686]}, {"class": "person", "id": 6, "bounding box (ltrb)": [1014, 364, 1087, 554]}, {"class": "person", "id": 1, "bounding box (ltrb)": [900, 554, 989, 752]}, {"class": "ball", "occlusion": 0, "id": 13, "bounding box (ltrb)": [766, 624, 800, 662]}, {"class": "ball", "occlusion": 0, "id": 12, "bounding box (ltrb)": [949, 613, 984, 651]}, {"class": "ball", "occlusion": 2, "id": 14, "bounding box (ltrb)": [870, 526, 887, 535]}]