[{"class": "ball", "occlusion": 0, "id": 13, "bounding box (ltrb)": [773, 624, 811, 662]}, {"class": "ball", "occlusion": 0, "id": 12, "bounding box (ltrb)": [1109, 678, 1155, 723]}, {"class": "ball", "occlusion": 0, "id": 14, "bounding box (ltrb)": [936, 425, 967, 454]}, {"class": "person", "id": 5, "bounding box (ltrb)": [389, 594, 513, 818]}, {"class": "person", "id": 6, "bounding box (ltrb)": [942, 381, 1014, 542]}, {"class": "person", "id": 4, "bounding box (ltrb)": [1119, 678, 1257, 918]}, {"class": "person", "id": 3, "bounding box (ltrb)": [892, 513, 972, 711]}, {"class": "person", "id": 2, "bounding box (ltrb)": [763, 570, 889, 789]}, {"class": "person", "id": 1, "bounding box (ltrb)": [922, 584, 1023, 788]}]