[{"class": "person", "id": 7, "bounding box (ltrb)": [494, 509, 589, 739]}, {"class": "person", "id": 5, "bounding box (ltrb)": [604, 450, 703, 675]}, {"class": "person", "id": 4, "bounding box (ltrb)": [476, 434, 583, 665]}, {"class": "person", "id": 2, "bounding box (ltrb)": [952, 505, 1055, 760]}, {"class": "person", "id": 3, "bounding box (ltrb)": [0, 510, 125, 769]}, {"class": "person", "id": 1, "bounding box (ltrb)": [590, 269, 689, 467]}, {"class": "ball", "occlusion": 0, "id": 13, "bounding box (ltrb)": [688, 463, 728, 506]}, {"class": "ball", "occlusion": 0, "id": 14, "bounding box (ltrb)": [490, 601, 534, 644]}]