[{"class": "ball", "occlusion": 0, "id": 13, "bounding box (ltrb)": [1198, 292, 1231, 327]}, {"class": "ball", "occlusion": 0, "id": 12, "bounding box (ltrb)": [720, 351, 757, 391]}, {"class": "ball", "occlusion": 0, "id": 14, "bounding box (ltrb)": [1078, 456, 1120, 499]}, {"class": "person", "id": 5, "bounding box (ltrb)": [962, 367, 1047, 574]}, {"class": "person", "id": 4, "bounding box (ltrb)": [936, 318, 992, 513]}, {"class": "person", "id": 7, "bounding box (ltrb)": [799, 357, 915, 566]}, {"class": "person", "id": 3, "bounding box (ltrb)": [1189, 230, 1299, 440]}, {"class": "person", "id": 2, "bounding box (ltrb)": [538, 319, 632, 557]}, {"class": "person", "id": 1, "bounding box (ltrb)": [1054, 479, 1211, 766]}]