[{"class": "person", "id": 7, "bounding box (ltrb)": [395, 398, 501, 616]}, {"class": "person", "id": 5, "bounding box (ltrb)": [505, 415, 607, 642]}, {"class": "person", "id": 4, "bounding box (ltrb)": [536, 362, 615, 582]}, {"class": "person", "id": 2, "bounding box (ltrb)": [712, 531, 800, 800]}, {"class": "person", "id": 3, "bounding box (ltrb)": [56, 500, 181, 731]}, {"class": "person", "id": 1, "bounding box (ltrb)": [417, 284, 548, 454]}, {"class": "ball", "occlusion": 0, "id": 13, "bounding box (ltrb)": [395, 462, 430, 503]}, {"class": "ball", "occlusion": 0, "id": 12, "bounding box (ltrb)": [514, 472, 560, 518]}, {"class": "ball", "occlusion": 0, "id": 14, "bounding box (ltrb)": [581, 393, 617, 430]}]