[{"class": "person", "id": 7, "bounding box (ltrb)": [778, 420, 862, 642]}, {"class": "person", "id": 5, "bounding box (ltrb)": [370, 434, 469, 686]}, {"class": "person", "id": 4, "bounding box (ltrb)": [660, 643, 818, 922]}, {"class": "person", "id": 2, "bounding box (ltrb)": [870, 357, 945, 579]}, {"class": "person", "id": 3, "bounding box (ltrb)": [948, 391, 1045, 625]}, {"class": "person", "id": 6, "bounding box (ltrb)": [1004, 234, 1103, 419]}, {"class": "ball", "occlusion": 0, "id": 13, "bounding box (ltrb)": [1005, 463, 1044, 505]}, {"class": "ball", "occlusion": 0, "id": 12, "bounding box (ltrb)": [1033, 276, 1062, 307]}, {"class": "ball", "occlusion": 0, "id": 14, "bounding box (ltrb)": [770, 483, 807, 522]}]