[{"class": "ball", "occlusion": 0, "id": 13, "bounding box (ltrb)": [865, 319, 900, 357]}, {"class": "ball", "occlusion": 0, "id": 12, "bounding box (ltrb)": [823, 499, 865, 540]}, {"class": "ball", "occlusion": 0, "id": 14, "bounding box (ltrb)": [1025, 451, 1060, 488]}, {"class": "person", "id": 5, "bounding box (ltrb)": [1347, 435, 1462, 688]}, {"class": "person", "id": 6, "bounding box (ltrb)": [488, 633, 614, 932]}, {"class": "person", "id": 4, "bounding box (ltrb)": [899, 228, 970, 406]}, {"class": "person", "id": 7, "bounding box (ltrb)": [810, 421, 903, 637]}, {"class": "person", "id": 3, "bounding box (ltrb)": [968, 367, 1066, 604]}, {"class": "person", "id": 2, "bounding box (ltrb)": [851, 327, 931, 572]}]