[{"class": "person", "id": 7, "bounding box (ltrb)": [829, 423, 921, 645]}, {"class": "person", "id": 5, "bounding box (ltrb)": [1068, 248, 1174, 429]}, {"class": "person", "id": 4, "bounding box (ltrb)": [543, 329, 626, 535]}, {"class": "person", "id": 2, "bounding box (ltrb)": [846, 347, 936, 569]}, {"class": "person", "id": 3, "bounding box (ltrb)": [970, 370, 1059, 593]}, {"class": "person", "id": 6, "bounding box (ltrb)": [766, 664, 902, 961]}, {"class": "ball", "occlusion": 0, "id": 12, "bounding box (ltrb)": [868, 500, 908, 540]}, {"class": "ball", "occlusion": 0, "id": 14, "bounding box (ltrb)": [1030, 435, 1062, 470]}]