[{"class": "ball", "occlusion": 0, "id": 13, "bounding box (ltrb)": [786, 428, 826, 471]}, {"class": "ball", "occlusion": 0, "id": 12, "bounding box (ltrb)": [933, 350, 972, 390]}, {"class": "ball", "occlusion": 0, "id": 14, "bounding box (ltrb)": [732, 250, 763, 282]}, {"class": "person", "id": 5, "bounding box (ltrb)": [707, 587, 829, 849]}, {"class": "person", "id": 6, "bounding box (ltrb)": [713, 220, 790, 394]}, {"class": "person", "id": 4, "bounding box (ltrb)": [1164, 312, 1245, 525]}, {"class": "person", "id": 7, "bounding box (ltrb)": [779, 410, 860, 630]}, {"class": "person", "id": 3, "bounding box (ltrb)": [868, 344, 962, 555]}, {"class": "person", "id": 2, "bounding box (ltrb)": [745, 348, 822, 571]}]