[{"class": "person", "id": 7, "bounding box (ltrb)": [1008, 348, 1092, 548]}, {"class": "person", "id": 5, "bounding box (ltrb)": [503, 261, 602, 457]}, {"class": "person", "id": 4, "bounding box (ltrb)": [970, 469, 1067, 713]}, {"class": "person", "id": 2, "bounding box (ltrb)": [881, 301, 949, 523]}, {"class": "person", "id": 3, "bounding box (ltrb)": [955, 278, 1036, 484]}, {"class": "person", "id": 1, "bounding box (ltrb)": [1343, 365, 1440, 609]}, {"class": "ball", "occlusion": 0, "id": 13, "bounding box (ltrb)": [1059, 403, 1094, 443]}, {"class": "ball", "occlusion": 0, "id": 12, "bounding box (ltrb)": [665, 368, 699, 403]}, {"class": "ball", "occlusion": 0, "id": 14, "bounding box (ltrb)": [1017, 537, 1057, 575]}]