[{"class": "person", "id": 7, "bounding box (ltrb)": [1054, 456, 1132, 647]}, {"class": "person", "id": 5, "bounding box (ltrb)": [1237, 376, 1327, 565]}, {"class": "person", "id": 4, "bounding box (ltrb)": [684, 425, 769, 633]}, {"class": "person", "id": 2, "bounding box (ltrb)": [1056, 509, 1154, 730]}, {"class": "person", "id": 3, "bounding box (ltrb)": [934, 487, 1021, 721]}, {"class": "person", "id": 6, "bounding box (ltrb)": [1248, 140, 1324, 293]}, {"class": "person", "id": 1, "bounding box (ltrb)": [1051, 679, 1200, 957]}, {"class": "ball", "occlusion": 0, "id": 13, "bounding box (ltrb)": [1056, 786, 1106, 832]}, {"class": "ball", "occlusion": 0, "id": 12, "bounding box (ltrb)": [1248, 432, 1284, 466]}, {"class": "ball", "occlusion": 0, "id": 14, "bounding box (ltrb)": [737, 492, 764, 523]}]