[{"class": "ball", "occlusion": 0, "id": 13, "bounding box (ltrb)": [668, 595, 716, 643]}, {"class": "ball", "occlusion": 0, "id": 12, "bounding box (ltrb)": [1182, 695, 1234, 743]}, {"class": "ball", "occlusion": 0, "id": 14, "bounding box (ltrb)": [808, 434, 845, 469]}, {"class": "person", "id": 5, "bounding box (ltrb)": [1195, 689, 1309, 941]}, {"class": "person", "id": 6, "bounding box (ltrb)": [909, 171, 962, 314]}, {"class": "person", "id": 4, "bounding box (ltrb)": [780, 374, 885, 539]}, {"class": "person", "id": 7, "bounding box (ltrb)": [795, 513, 877, 717]}, {"class": "person", "id": 3, "bounding box (ltrb)": [679, 576, 780, 827]}, {"class": "person", "id": 2, "bounding box (ltrb)": [835, 568, 936, 818]}, {"class": "person", "id": 1, "bounding box (ltrb)": [299, 648, 430, 941]}]